{"target": 6, "speaker": 67, "voice": 8, "activity": 9, "detection": 15, "improved": 5, "vector": 11, "estimation": 4, "unknown": 11, "number": 36, "maokui": 1, "desh": 1, "raj": 4, "zili": 1, "huang": 5, "jun": 1, "du": 2, "zhuo": 1, "chen": 4, "shinji": 1, "watanabe": 5, "university": 2, "science": 1, "technology": 3, "china": 2, "hefei": 1, "center": 1, "language": 6, "speech": 40, "processing": 15, "johns": 1, "hopkins": 1, "baltimore": 1, "md": 1, "microsoft": 2, "corp": 1, "redmond": 1, "wa": 1, "jundu": 1, "ustc": 1, "edu": 1, "cn": 1, "arxiv": 7, "eess": 1, "aug": 1, "abstract": 1, "ts": 64, "vad": 66, "promising": 3, "diarization": 61, "highly": 1, "overlapped": 4, "original": 2, "model": 24, "requires": 2, "xed": 6, "known": 2, "speakers": 58, "limits": 1, "application": 2, "real": 2, "conversations": 3, "paper": 3, "extend": 2, "numbers": 5, "achieved": 2, "steps": 2, "initial": 9, "applied": 3, "followed": 6, "network": 11, "output": 16, "masking": 2, "according": 1, "estimate": 11, "investigate": 3, "different": 19, "methods": 8, "including": 1, "clusteringbased": 2, "region": 6, "proposal": 5, "networks": 6, "estimating": 2, "vectors": 20, "systems": 16, "complementary": 4, "strengths": 3, "propose": 4, "fusion": 7, "based": 18, "method": 12, "combine": 3, "frame": 7, "level": 4, "decisions": 1, "initialization": 15, "demonstrate": 1, "experiments": 6, "variants": 4, "libricss": 24, "meeting": 7, "corpus": 2, "proposed": 5, "approach": 7, "improve": 1, "der": 13, "relative": 5, "varying": 3, "improvement": 8, "better": 5, "downstream": 3, "asr": 11, "performance": 19, "approaching": 1, "oracle": 9, "segments": 13, "index": 1, "terms": 7, "multi": 7, "overlap": 17, "introduction": 1, "refers": 2, "task": 1, "segmenting": 1, "recording": 12, "homogeneous": 1, "speci": 2, "regions": 2, "conventional": 2, "involves": 1, "applying": 1, "sad": 4, "clustering": 17, "dimensional": 2, "embeddings": 8, "neural": 11, "extracted": 3, "small": 4, "subsegments": 2, "optionally": 1, "resegmentation": 3, "step": 1, "framework": 2, "inherently": 2, "makes": 1, "single": 7, "assumption": 2, "subsegment": 4, "assigned": 2, "label": 3, "hard": 1, "efforts": 1, "solve": 1, "problem": 2, "leveraging": 2, "separate": 2, "module": 3, "identi": 2, "es": 3, "containing": 6, "hidden": 1, "markov": 1, "models": 10, "hmms": 1, "additional": 1, "labels": 1, "overlapping": 11, "detected": 1, "alternate": 1, "popular": 1, "recent": 2, "years": 1, "applies": 1, "end": 9, "trained": 9, "supervision": 1, "simulated": 6, "mixtures": 5, "includes": 1, "eend": 2, "rpn": 14, "naturally": 2, "handle": 4, "overlaps": 3, "challenging": 1, "data": 10, "sets": 3, "demonstrated": 1, "chime": 4, "challenge": 4, "inspired": 2, "advances": 1, "extraction": 4, "speakerbeam": 1, "voicefilter": 1, "personal": 2, "utilize": 1, "enrollment": 1, "information": 4, "time": 4, "frequency": 1, "masks": 1, "indicate": 1, "supervised": 1, "generates": 1, "outputs": 7, "wise": 1, "posteriors": 1, "conditional": 1, "dependence": 1, "best": 7, "contains": 3, "duration": 4, "evaluation": 7, "set": 13, "improving": 1, "baseline": 2, "agglomerative": 2, "hierarchical": 2, "ahc": 2, "absolute": 1, "error": 5, "rate": 4, "limited": 1, "assumes": 1, "priori": 1, "nodes": 10, "corresponds": 1, "inference": 11, "hinders": 1, "recordings": 10, "commonly": 1, "happen": 1, "natural": 1, "meetings": 4, "furthermore": 3, "depends": 1, "poor": 1, "lead": 1, "worse": 1, "iterations": 3, "convergence": 2, "address": 1, "limitations": 1, "work": 4, "long": 4, "form": 1, "relies": 1, "typically": 1, "estimates": 2, "predict": 1, "consequently": 1, "manipulates": 1, "correspond": 1, "effectiveness": 1, "rpns": 1, "obtaining": 1, "contain": 3, "weighted": 2, "mean": 1, "strategy": 7, "decision": 1, "optimal": 1, "conducted": 2, "dataset": 8, "extension": 1, "improves": 1, "compared": 6, "strong": 1, "consistent": 2, "demonstrates": 1, "robustness": 1, "technique": 1, "provides": 1, "report": 2, "effect": 2, "integrated": 1, "transcription": 1, "concatenated": 2, "minimum": 2, "permutation": 3, "word": 2, "cpwer": 5, "mixed": 3, "audio": 8, "rttm": 2, "vbx": 13, "sc": 24, "iteration": 2, "post": 2, "thresholding": 1, "ltering": 1, "short": 4, "segment": 1, "deletion": 1, "pause": 1, "concatenation": 1, "figure": 2, "stage": 1, "decoding": 4, "pipeline": 3, "nd": 1, "comparable": 1, "fig": 2, "general": 1, "consists": 5, "external": 2, "nally": 2, "convert": 1, "sequence": 1, "contained": 1, "nist": 1, "style": 4, "les": 1, "conduct": 1, "investigations": 2, "pertaining": 1, "aspects": 1, "key": 1, "contribution": 2, "enabling": 1, "particular": 1, "introduce": 1, "deal": 1, "lower": 2, "training": 17, "developed": 1, "consisted": 1, "exactly": 1, "permissible": 1, "participants": 1, "life": 1, "scenarios": 2, "adhere": 1, "restrictions": 1, "comprises": 1, "consisting": 2, "multichannel": 1, "generated": 3, "mixing": 1, "test": 2, "utterances": 5, "librispeech": 8, "sessions": 2, "session": 2, "approximately": 2, "hour": 1, "minute": 1, "mini": 1, "ratios": 1, "ranging": 2, "ratio": 3, "fraction": 1, "speaking": 2, "audios": 1, "recorded": 1, "regular": 1, "room": 1, "seven": 1, "channel": 2, "circular": 1, "microphone": 1, "array": 2, "selected": 3, "simulations": 1, "noise": 1, "reverberation": 1, "added": 1, "arti": 2, "cially": 2, "mixture": 1, "created": 1, "entire": 2, "comprised": 1, "amounting": 1, "hours": 1, "takes": 2, "features": 3, "log": 1, "mel": 1, "lter": 3, "banks": 2, "input": 4, "corresponding": 5, "predicts": 2, "activities": 2, "simultaneously": 1, "formally": 1, "acous": 1, "iv": 14, "discarding": 2, "selecting": 1, "train": 1, "randomly": 2, "handling": 3, "estimated": 5, "exceeds": 1, "discard": 2, "frequent": 1, "left": 1, "branch": 2, "pad": 1, "right": 1, "tic": 1, "observations": 1, "xt": 2, "rd": 1, "gn": 5, "rl": 1, "arg": 1, "max": 1, "ytn": 1, "denotes": 2, "probability": 2, "active": 1, "distribution": 1, "modeled": 1, "parameters": 1, "learned": 1, "architecture": 1, "convolutional": 1, "layers": 1, "extract": 1, "acoustic": 2, "raw": 1, "sd": 1, "component": 2, "comprising": 2, "layer": 2, "bidirectional": 1, "lstm": 2, "projection": 1, "blstmp": 2, "splices": 1, "produces": 3, "spliced": 1, "passed": 1, "class": 2, "silence": 1, "probabilities": 1, "chosen": 1, "maximum": 2, "case": 4, "extractor": 3, "augmented": 1, "fold": 1, "speed": 1, "perturbation": 1, "targets": 1, "current": 1, "directly": 2, "forced": 1, "alignments": 1, "underlying": 1, "utterance": 2, "described": 3, "higher": 1, "presents": 1, "challenges": 1, "need": 2, "say": 1, "devise": 1, "way": 1, "solution": 3, "straightforward": 1, "existing": 1, "initialized": 4, "means": 4, "incur": 1, "computational": 1, "overhead": 1, "equal": 1, "effort": 1, "required": 3, "cases": 2, "depending": 1, "larger": 3, "smaller": 3, "solutions": 1, "select": 1, "longest": 1, "non": 3, "situation": 1, "rarely": 1, "occurs": 1, "chose": 1, "hole": 1, "datasets": 1, "happens": 1, "loss": 1, "minimized": 1, "assign": 3, "remaining": 1, "dummy": 2, "abandoned": 1, "generating": 1, "nal": 3, "procedure": 1, "authors": 1, "accuracy": 1, "depended": 1, "investigated": 1, "strategies": 3, "initializing": 1, "section": 4, "categorize": 1, "examine": 1, "spectral": 4, "tdnn": 2, "stats": 1, "classi": 3, "er": 1, "viterbi": 1, "divided": 1, "window": 1, "size": 1, "stride": 1, "voxceleb": 2, "scored": 1, "pairwise": 2, "cosine": 1, "scoring": 2, "clusters": 1, "auto": 2, "tuning": 2, "criterion": 1, "binarization": 1, "normalized": 1, "eigengap": 1, "vb": 2, "hmm": 4, "embedding": 2, "xvector": 1, "bayesian": 2, "iteratively": 1, "ne": 2, "soft": 1, "probabilistic": 1, "alignment": 1, "distributions": 1, "able": 1, "determine": 1, "plda": 1, "posterior": 1, "matrix": 1, "combines": 1, "segmentation": 3, "jointly": 1, "optimizes": 1, "objective": 1, "function": 1, "boundary": 1, "prediction": 1, "cation": 6, "components": 1, "clustered": 1, "maximal": 1, "suppression": 1, "partial": 1, "gives": 1, "details": 1, "mentioned": 1, "accurate": 1, "effective": 2, "detecting": 1, "change": 1, "granularity": 1, "hand": 1, "detect": 1, "advantages": 1, "order": 1, "compute": 2, "reliable": 1, "novel": 2, "majority": 1, "voting": 1, "space": 2, "map": 1, "common": 1, "grouped": 1, "longer": 1, "combinations": 1, "metric": 1, "group": 1, "vadsn": 1, "sth": 2, "weights": 2, "timation": 1, "weight": 1, "factor": 3, "nth": 2, "diariza": 1, "tion": 1, "satis": 1, "uniform": 1, "vadns": 1, "indicator": 1, "variable": 1, "existence": 1, "experimental": 1, "table": 9, "jaccard": 1, "jer": 6, "respective": 1, "spk": 26, "observed": 2, "conditions": 2, "achieves": 1, "custom": 1, "decode": 1, "losing": 1, "drops": 1, "drastically": 1, "indicates": 1, "heuristic": 1, "choose": 1, "suitable": 1, "hungarian": 1, "refer": 1, "inter": 1, "silences": 1, "init": 3, "avg": 1, "initializations": 3, "investigation": 1, "ders": 3, "break": 1, "condition": 1, "note": 1, "prior": 1, "uses": 1, "aware": 4, "prominent": 1, "close": 3, "surprisingly": 1, "performed": 1, "did": 1, "achieve": 1, "evaluated": 2, "provided": 2, "retained": 1, "combined": 1, "providing": 1, "fusions": 1, "dover": 5, "lap": 5, "slight": 1, "simply": 1, "individual": 1, "impact": 2, "built": 2, "hybrid": 1, "dnn": 2, "kaldi": 2, "recipe": 1, "rates": 1, "cpw": 1, "wer": 2, "ers": 1, "computed": 1, "concatenating": 1, "reference": 1, "hypothesis": 1, "pairs": 1, "nding": 1, "minimizes": 1, "total": 1, "cpwers": 1, "going": 1, "signi": 1, "improvements": 2, "high": 1, "indicating": 1, "separation": 6, "satisfactorily": 1, "transcribe": 1, "conclusion": 1, "adapted": 1, "art": 1, "ef": 1, "cacy": 1, "notably": 1, "outperformed": 1, "customized": 1, "simple": 3, "multiinitial": 1, "suggested": 1, "necessary": 1, "bottleneck": 1, "future": 1, "avoid": 1, "issue": 1, "acknowledgments": 1, "reported": 1, "started": 1, "jsalt": 1, "support": 1, "amazon": 1, "google": 1, "thank": 1, "tianyan": 1, "zhou": 2, "xiaofei": 1, "wang": 4, "zhong": 1, "meng": 2, "contributions": 1, "collecting": 1, "supported": 1, "strategic": 1, "priority": 1, "research": 2, "program": 1, "chinese": 1, "academy": 1, "sciences": 1, "grant": 1, "xdc": 1, "references": 1, "miro": 1, "bozonnet": 2, "evans": 2, "fredouille": 2, "friedland": 2, "vinyals": 2, "review": 1, "ieee": 14, "transactions": 3, "vol": 9, "pp": 13, "tranter": 1, "reynolds": 1, "overview": 1, "automatic": 2, "garcia": 3, "romero": 3, "snyder": 2, "sell": 3, "povey": 6, "mccree": 1, "deep": 2, "international": 8, "conference": 8, "acoustics": 8, "signal": 8, "icassp": 9, "sun": 1, "jiang": 1, "zhang": 2, "yin": 1, "lee": 1, "enhancing": 2, "dihard": 1, "interspeech": 7, "dehak": 2, "kenny": 1, "dumouchel": 1, "ouellet": 1, "analysis": 4, "veri": 2, "variani": 1, "lei": 1, "mcdermott": 1, "lopez": 3, "moreno": 3, "gonzalez": 1, "dominguez": 1, "footprint": 1, "text": 1, "dependent": 1, "khudanpur": 5, "robust": 1, "recognition": 5, "lia": 1, "eurecom": 1, "rt": 1, "enhancements": 1, "modelling": 1, "cluster": 1, "puri": 1, "subspace": 1, "boakye": 1, "trueba": 1, "hornero": 1, "multiparty": 1, "huijbregts": 1, "van": 1, "leeuwen": 1, "jong": 1, "pass": 1, "hagerer": 1, "pandit": 1, "eyben": 1, "schuller": 1, "rnn": 1, "semantic": 1, "kunesova": 1, "hru": 1, "zaj": 1, "radova": 1, "purposes": 1, "specom": 1, "bullock": 1, "bredin": 1, "garc": 3, "perera": 2, "abs": 6, "fujita": 2, "horiguchi": 1, "xue": 1, "nagamatsu": 1, "reformulating": 1, "shao": 1, "medennikov": 1, "korenevsky": 1, "prisyach": 1, "khokhlov": 1, "korenevskaya": 1, "sorokin": 1, "timofeeva": 1, "mitrofanov": 1, "andrusenko": 1, "podluzhny": 1, "laptev": 1, "romanenko": 1, "dinner": 1, "party": 1, "scenario": 1, "mandel": 1, "barker": 1, "vincent": 1, "tackling": 1, "multispeaker": 1, "unsegmented": 1, "mol": 1, "kova": 1, "delcroix": 1, "kinoshita": 1, "higuchi": 1, "ogawa": 1, "nakatani": 1, "beamformer": 1, "muckenhirn": 1, "wilson": 1, "sridhar": 1, "wu": 2, "hershey": 2, "saurous": 1, "weiss": 1, "jia": 1, "targeted": 1, "conditioned": 2, "spectrogram": 1, "ding": 1, "yiin": 1, "chang": 1, "wan": 1, "yoshioka": 1, "lu": 1, "luo": 1, "li": 1, "continuous": 1, "submission": 1, "panayotov": 1, "public": 1, "domain": 1, "books": 1, "ning": 1, "liu": 1, "tang": 1, "diez": 1, "burget": 2, "rohdin": 1, "cernocky": 1, "park": 1, "chan": 1, "chiu": 1, "zoph": 1, "cubuk": 1, "le": 1, "specaugment": 1, "augmentation": 1, "nagrani": 1, "chung": 1, "zisserman": 1, "largescale": 1, "denisov": 1, "erdogan": 1, "integration": 1, "description": 1, "comparison": 1, "spoken": 2, "workshop": 2, "slt": 2, "stolcke": 1, "combining": 1, "ghoshal": 1, "boulianne": 1, "glembek": 1, "goel": 1, "hannemann": 1, "motl": 1, "cek": 1, "qian": 1, "schwarz": 1, "silovsky": 1, "stemmer": 1, "vesely": 1, "toolkit": 1}